calc_elem_angles.py
clean_sim.py
cr_get_analytical_solutions.py
cr_get_modelling_errors.py
cr_trig_create.py
cr_trig_parse_gmsh.py
grid_extralines_gen_decouplings.py
grid_gen_decouplings.py
grid_gen_depth_decoupling.py
grid_homogenize.py
grid_plot_elem_angles.py
grid_plot_wireframe.py
grid_rotate.py
grid_translate.py
grid_translate_model.py
init_sim.py
sd_plot.py
sens_center_plot.py
td_clean.py
td_correct_temperature.py
td_init.py
td_plot.py
td_residuals.py
td_run_all_local.py
td_test.py
temp_corr.py
volt_correct_temperature.py
volt_histogram.py
crtomo/__init__.py
crtomo/analytical_solution.py
crtomo/binaries.py
crtomo/cfg.py
crtomo/configManager.py
crtomo/debug.py
crtomo/eitManager.py
crtomo/grid.py
crtomo/mpl.py
crtomo/mpl_setup.py
crtomo/nodeManager.py
crtomo/parManager.py
crtomo/plotManager.py
crtomo/status.py
crtomo/tdManager.py
crtomo/debug_data/elec_20elecs.dat
crtomo/debug_data/elec_40elec.dat
crtomo/debug_data/elec_40elecs.dat
crtomo/debug_data/elem_20elecs.dat
crtomo/debug_data/elem_40elecs.dat
crtomo_tools-0.2.0.dist-info/METADATA
crtomo_tools-0.2.0.dist-info/RECORD
crtomo_tools-0.2.0.dist-info/WHEEL
crtomo_tools-0.2.0.dist-info/entry_points.txt
crtomo_tools-0.2.0.dist-info/top_level.txt
