Metadata-Version: 2.1
Name: crtomo-tools
Version: 0.2.0
Summary: CRTomo Python Toolbox
Home-page: https://github.com/geophysics-ubonn/crtomo_tools
Author: Maximilian Weigand
Author-email: mweigand@geo.uni-bonn.de
License: MIT
Platform: UNKNOWN
Requires-Dist: numpy
Requires-Dist: scipy
Requires-Dist: matplotlib
Requires-Dist: shapely
